toon/__init__.py
toon/util/priority.py
toon/util/clock.cpython-38-x86_64-linux-gnu.so
toon/util/__init__.py
toon/anim/player.cpython-38-x86_64-linux-gnu.so
toon/anim/easing.cpython-38-x86_64-linux-gnu.so
toon/anim/track.cpython-38-x86_64-linux-gnu.so
toon/anim/__init__.py
toon/anim/interpolators.cpython-38-x86_64-linux-gnu.so
toon/input/mpdevice.py
toon/input/_tbprocess.py
toon/input/device.py
toon/input/__init__.py
toon-0.15.9.dist-info/WHEEL
toon-0.15.9.dist-info/METADATA
toon-0.15.9.dist-info/top_level.txt
toon-0.15.9.dist-info/RECORD
toon-0.15.9.dist-info/LICENSE.txt
tests/input/test_device.py
tests/input/test_mpdevice.py
tests/input/mockdevices.py
tests/input/__init__.py
