Metadata-Version: 2.1
Name: toon
Version: 0.15.9
Summary: Tools for neuroscience experiments
Home-page: https://github.com/aforren1/toon
Author: Alexander Forrence
Author-email: alex.forrence@gmail.com
License: MIT
Keywords: psychophysics neuroscience input experiment
Platform: UNKNOWN
Classifier: Development Status :: 4 - Beta
Classifier: Intended Audience :: Science/Research
Classifier: License :: OSI Approved :: MIT License
Classifier: Programming Language :: Python :: 3
Classifier: Programming Language :: Python :: 3.6
Classifier: Programming Language :: Python :: 3.7
Classifier: Programming Language :: Python :: 3.8
Classifier: Programming Language :: Python :: 3.9
Requires-Dist: numpy (>=1.16.1)
Requires-Dist: psutil
